example_pkg/__init__.py
example_pkg/hello.py
example_pkg_your_cohey0727-0.0.4.dist-info/METADATA
example_pkg_your_cohey0727-0.0.4.dist-info/WHEEL
example_pkg_your_cohey0727-0.0.4.dist-info/top_level.txt
example_pkg_your_cohey0727-0.0.4.dist-info/RECORD
