Metadata-Version: 2.1
Name: example-pkg-your-cohey0727
Version: 0.0.4
Summary: A small example package
Home-page: https://github.com/Cohey0727/pypi_packaging_tutorial
Author: Kohei Okamoto
Author-email: ohayousagi.ac.kook0727@gmail.com
License: UNKNOWN
Platform: UNKNOWN
Classifier: Programming Language :: Python :: 3
Classifier: License :: OSI Approved :: MIT License
Classifier: Operating System :: OS Independent
Requires-Python: >=3.6
